dpvs/__init__.py
dpvs/callbacks/__init__.py
dpvs/callbacks/readme.md
dpvs/configs/__init__.py
dpvs/configs/model/hpnet.yaml
dpvs/configs/model/none.yaml
dpvs/configs/readme.md
dpvs/configs/sklearn.yaml
dpvs/configs/torch.yaml
dpvs/datasets/__init__.py
dpvs/datasets/dataset.py
dpvs/datasets/readme.md
dpvs/datasets/utils.py
dpvs/datasets/walk_ds.py
dpvs/engines/ignite_run.py
dpvs/engines/readme.md
dpvs/engines/sklearn_run.py
dpvs/logging/__init__.py
dpvs/metrics/__init__.py
dpvs/metrics/readme.md
dpvs/model/hpnet/__init__.py
dpvs/model/hpnet/feature.py
dpvs/model/hpnet/symptom.py
dpvs/model/hpnet/trend.py
dpvs/model/readme.md
dpvs/model/sklearn_models.py
dpvs/model/sparsemax.py
dpvs/model/vision_models.py
dpvs/readme.md
dpvs/train.py
dpvs/utils/__init__.py
dpvs/utils/_io.py
dpvs/utils/_numpy.py
dpvs/utils/_torch.py
dpvs/utils/wrapper.py
dpvs-0.1.3.dist-info/WHEEL
dpvs-0.1.3.dist-info/METADATA
dpvs-0.1.3.dist-info/RECORD
