Metadata-Version: 2.1
Name: dpvs
Version: 0.1.3
Summary: 
Author: dennislblog
Author-email: dennisl@udel.edu
Requires-Python: >=3.8,<4.0
Classifier: Programming Language :: Python :: 3
Classifier: Programming Language :: Python :: 3.8
Classifier: Programming Language :: Python :: 3.9
Classifier: Programming Language :: Python :: 3.10
Requires-Dist: hydra-core (>=1.2.0,<2.0.0)
Requires-Dist: ipython (>=8.5.0,<9.0.0)
Requires-Dist: tables (>=3.7.0,<4.0.0)
Requires-Dist: xgboost (>=1.6.2,<2.0.0)
